{
  "project_info": {
    "project_number": "640196743442",
    "project_id": "englishcenter-2021",
    "storage_bucket": "englishcenter-2021.appspot.com"
  },
  "client": [
    {
      "client_info": {
        "mobilesdk_app_id": "1:640196743442:android:581b486a1006c014a0e3cb",
        "android_client_info": {
          "package_name": "com.ec.app.english_center"
        }
      },
      "oauth_client": [
        {
          "client_id": "640196743442-p3pgpjd4vp445u4r3mdout4fosddvfgc.apps.googleusercontent.com",
          "client_type": 1,
          "android_info": {
            "package_name": "com.ec.app.english_center",
            "certificate_hash": "7174fa25c9a39bfbe2567b687029d8a0ebb3fdfd"
          }
        },
        {
          "client_id": "640196743442-2at53t9mbed88vdgbdad0k21qfet1mk6.apps.googleusercontent.com",
          "client_type": 3
        }
      ],
      "api_key": [
        {
          "current_key": "AIzaSyDca9xFp0q4yoksC5kuq_kus_rLS6V0V9Y"
        }
      ],
      "services": {
        "appinvite_service": {
          "other_platform_oauth_client": [
            {
              "client_id": "640196743442-2at53t9mbed88vdgbdad0k21qfet1mk6.apps.googleusercontent.com",
              "client_type": 3
            }
          ]
        }
      }
    }
  ],
  "configuration_version": "1"
}